.dockerignore
.pylintrc
AUTHORS
ChangeLog
Dockerfile
LICENSE
MANIFEST.in
README.md
requirements.txt
setup.cfg
setup.py
test-requirements.txt
tox.ini
kelly_criterion/__init__.py
kelly_criterion/kelly_criterion.py
kelly_criterion.egg-info/PKG-INFO
kelly_criterion.egg-info/SOURCES.txt
kelly_criterion.egg-info/dependency_links.txt
kelly_criterion.egg-info/entry_points.txt
kelly_criterion.egg-info/not-zip-safe
kelly_criterion.egg-info/pbr.json
kelly_criterion.egg-info/requires.txt
kelly_criterion.egg-info/top_level.txt
tests/__init__.py
tests/test_kelly_criterion.py