Metadata-Version: 1.1
Name: kelly-criterion
Version: 1.2.0
Summary: Kelly Criterion Calculator
Home-page: https://github.com/kelly-direct/kelly-criterion
Author: Tibor Kiss
Author-email: tibor.kiss@gmail.com
License: UNKNOWN
Keywords: kelly-criterion kelly money-management
Platform: UNKNOWN
Classifier: Development Status :: 6 - Mature
Classifier: Programming Language :: Python :: 3.7
Classifier: Operating System :: OS Independent
Classifier: Topic :: Office/Business :: Financial :: Investment
